{"package": "org.dezlowng.glw", "name": "\u041f\u043e\u0441\u043b\u0435\u0434\u043d\u0435\u0435 \u0436\u0435\u043b\u0430\u043d\u0438\u0435 \u0434\u0435\u0432\u043e\u0447\u043a\u0438", "icon_name": "\u041f\u043e\u0441\u043b\u0435\u0434\u043d\u0435\u0435 \u0436\u0435\u043b\u0430\u043d\u0438\u0435 \u0434\u0435\u0432\u043e\u0447\u043a\u0438", "version": "1.1", "numeric_version": 1, "orientation": "sensorLandscape", "permissions": ["VIBRATE"], "include_pil": false, "include_sqlite": false, "layout": null, "source": false, "expansion": false, "store": "none", "update_icons": true, "update_always": true, "heap_size": "3"}